marstar/__init__.py
marstar-0.1.1.dist-info/licenses/LICENSE
marstar-0.1.1.dist-info/METADATA
marstar-0.1.1.dist-info/WHEEL
marstar-0.1.1.dist-info/top_level.txt
marstar-0.1.1.dist-info/RECORD
