Metadata-Version: 2.4
Name: marstar
Version: 0.1.1
Summary: Required NumPy,make sure that is installed.An ultimate game platform,available for Tic-Tac-Toe game and Murphy,the best number game ever.Use marstar.guide() to view the guide of this game,required NumPy.
Author: Marcy
Requires-Python: >=3.7
License-File: LICENSE
Dynamic: author
Dynamic: license-file
Dynamic: requires-python
